README.md
setup.cfg
setup.py
sidermit/__init__.py
sidermit/exceptions.py
sidermit.egg-info/PKG-INFO
sidermit.egg-info/SOURCES.txt
sidermit.egg-info/dependency_links.txt
sidermit.egg-info/requires.txt
sidermit.egg-info/top_level.txt
sidermit/city/__init__.py
sidermit/city/demand.py
sidermit/city/graph.py
sidermit/optimization/__init__.py
sidermit/optimization/constrains.py
sidermit/optimization/infrastructure_cost.py
sidermit/optimization/operators_cost.py
sidermit/optimization/optimizer.py
sidermit/optimization/users_cost.py
sidermit/optimization/preoptimization/__init__.py
sidermit/optimization/preoptimization/assignment.py
sidermit/optimization/preoptimization/extended_graph.py
sidermit/optimization/preoptimization/hyper_path.py
sidermit/publictransportsystem/__init__.py
sidermit/publictransportsystem/mode.py
sidermit/publictransportsystem/network.py
sidermit/publictransportsystem/passenger.py
tests/__init__.py
tests/test_demand.py
tests/test_extended_graph.py
tests/test_graph.py
tests/test_transport_mode.py
tests/test_transport_network.py
tests/test_transport_user.py