Metadata-Version: 1.1
Name: sidermit
Version: 0.0.20
Summary: optimize public transport system on a city graph based on one CBD and zones
Home-page: https://github.com/SIDERMIT/optimizer
Author: Felipe Vera
Author-email: fvera@transapp.cl
License: gpl-3.0
Download-URL: https://github.com/SIDERMIT/optimizer/archive/v0.0.20.tar.gz
Keywords: public transport,optimize
Platform: UNKNOWN
Classifier: Development Status :: 3 - Alpha
Classifier: Intended Audience :: Developers
Classifier: License :: OSI Approved :: GNU General Public License v3 (GPLv3)
Classifier: Operating System :: OS Independent
Classifier: Programming Language :: Python
Classifier: Programming Language :: Python :: 3
Classifier: Programming Language :: Python :: 3 :: Only
Classifier: Programming Language :: Python :: 3.7
